qtile_lxa/__init__.py
qtile_lxa/assets/icons/brightness-dark.png
qtile_lxa/assets/icons/brightness-light.png
qtile_lxa/assets/icons/close.png
qtile_lxa/assets/icons/inactive-dark.png
qtile_lxa/assets/icons/inactive-light.png
qtile_lxa/assets/icons/lock.png
qtile_lxa/assets/icons/logout.png
qtile_lxa/assets/icons/mic-mute-dark.png
qtile_lxa/assets/icons/mic-mute-light.png
qtile_lxa/assets/icons/mic-normal-dark.png
qtile_lxa/assets/icons/mic-normal-light.png
qtile_lxa/assets/icons/restart.png
qtile_lxa/assets/icons/shutdown.png
qtile_lxa/assets/icons/sleep.png
qtile_lxa/assets/icons/theme-changer.png
qtile_lxa/assets/icons/volume-high-dark.png
qtile_lxa/assets/icons/volume-high-light.png
qtile_lxa/assets/icons/volume-low-dark.png
qtile_lxa/assets/icons/volume-low-light.png
qtile_lxa/assets/icons/volume-mute-dark.png
qtile_lxa/assets/icons/volume-mute-light.png
qtile_lxa/assets/icons/volume-normal-dark.png
qtile_lxa/assets/icons/volume-normal-light.png
qtile_lxa/assets/icons/not_in_use/circled-pause-dark.png
qtile_lxa/assets/icons/not_in_use/circled-pause-light.png
qtile_lxa/assets/icons/not_in_use/circled-play-dark.png
qtile_lxa/assets/icons/not_in_use/circled-play-light.png
qtile_lxa/assets/k8s/templates/scripts/master_userdata.sh.j2
qtile_lxa/assets/k8s/templates/scripts/worker_post_start.sh.j2
qtile_lxa/assets/k8s/templates/scripts/worker_pre_remove.sh.j2
qtile_lxa/assets/k8s/templates/scripts/worker_userdata.sh.j2
qtile_lxa/assets/sounds/volume-notification.wav
qtile_lxa/assets/vagrant/templates/vagrantfile_vm.j2
qtile_lxa/assets/vagrant/templates/vagrantfile_vm_group.j2
qtile_lxa/assets/wallpapers/hacker/lxa_hacker_terminal.png
qtile_lxa/assets/wallpapers/nature/lxa_nature_arch.png
qtile_lxa/assets/wallpapers/scifi/lxa_sifi_arch.png
qtile_lxa/utils/__init__.py
qtile_lxa/utils/atomic_writer.py
qtile_lxa/utils/auto_screen_lock.py
qtile_lxa/utils/data_manager.py
qtile_lxa/utils/network.py
qtile_lxa/utils/notification.py
qtile_lxa/utils/process_lock.py
qtile_lxa-0.0.9.dist-info/licenses/LICENSE
qtile_lxa-0.0.9.dist-info/METADATA
qtile_lxa-0.0.9.dist-info/WHEEL
qtile_lxa-0.0.9.dist-info/top_level.txt
qtile_lxa-0.0.9.dist-info/RECORD
