Metadata-Version: 2.4
Name: qtile-lxa
Version: 0.0.9
Summary: QtileLXA is a modular extension suite for the Qtile window manager, featuring custom widgets, dynamic theming, video wallpapers, and system controls, all designed to enhance and automate your Qtile desktop experience.
Author-email: Pankaj Jackson <pankajackson@live.co.uk>
License-Expression: MIT
Project-URL: Homepage, https://github.com/pankajackson/qtile-lxa
Project-URL: Bug Tracker, https://github.com/pankajackson/qtile-lxa/issues
Project-URL: Source, https://github.com/pankajackson/qtile-lxa
Keywords: qtile,widgets,feature,wm,window manager
Classifier: Programming Language :: Python :: 3.10
Classifier: Programming Language :: Python :: 3.11
Classifier: Programming Language :: Python :: 3.12
Classifier: Programming Language :: Python :: 3.13
Classifier: Development Status :: 3 - Alpha
Classifier: Intended Audience :: End Users/Desktop
Classifier: Operating System :: POSIX :: Linux
Classifier: Topic :: Utilities
Requires-Python: >=3.10
License-File: LICENSE
Requires-Dist: qtile
Requires-Dist: qtile-extras
Requires-Dist: elasticsearch
Requires-Dist: kubernetes
Requires-Dist: GPUtil
Requires-Dist: pywal
Requires-Dist: psutil
Requires-Dist: docker
Requires-Dist: podman
Requires-Dist: jinja2
Dynamic: license-file
